[
  {
    "doctype": "synthesis",
    "name": "Mbyá [gun-arg] (Mbyá de Argentina)",
    "glottolog_code": "TODO",
    "short_name": "TODO",
    "alternate_names": [
      "TODO"
    ],
    "iso_codes": [
      "TODO"
    ],
    "synthesis": "This synthesis closely follows Thomas' (2014) analysis of Mbyá given that it is the only description for the variety spoken in Argentina. Following Thomas, we consider Mbyá to have contrastive oral and nasal vowels. We adopt the following processes from Thomas: (1) rightward MPP, nasalization of the locative {-pɨ} and diminutive suffix {-ʔi} to [mɨ̃] and [ʔĩ], respectively, after a root-final nasal vowel. In this process the glottal stop /ʔ/ from the diminutive suffix is not nasalized; (2) leftward LDNH, a root-final stressed nasal vowel spreads its nasalization, nasalizing oral vowels and the voiced segments /ɾ, w, ɡʷ, β, dʒ/. Oral stops /p, t, tʃ, k, kʷ, ʔ/ act as transparent to this process; (3) rightward MPP, in a root-suffix compound a root-final nasal vowel triggers pre-nasalization of oral stops /p, t, k, kʷ/ to [mb, nd, ŋɡ, ŋɡʷ], respectively.  We diverge from Thomas' analysis in the following ways: (1) we consider nasal consonants to be underlying and undergo a process of post-oralization before an oral vowel, i.e. /m, n, ŋ, ŋʷ/ to [mb, nd, ŋɡ, ŋɡʷ], respectively (leftward LO). We infer that this process occurs in prefixes, roots, and suffixes, based on the following data points from Thomas: kũɲã+ŋɡʷe 'woman', õ+mãnõ+mba 'they all died', ɲãnẽ+mbaraka 'our guitar' (p. 84-85).",
    "natural_classes": [
      {
        "symbol": "T",
        "members": [
          "p",
          "t",
          "k",
          "kʷ",
          "tʃ",
          "ʔ"
        ]
      },
      {
        "symbol": "D",
        "members": [
          "ɡʷ",
          "dʒ"
        ]
      },
      {
        "symbol": "N",
        "members": [
          "m",
          "n",
          "ŋ",
          "ŋʷ"
        ]
      },
      {
        "symbol": "Z",
        "members": [
          "β"
        ]
      },
      {
        "symbol": "S",
        "members": [
          "h"
        ]
      },
      {
        "symbol": "R",
        "members": [
          "w",
          "ɾ"
        ]
      },
      {
        "symbol": "V",
        "members": [
          "i",
          "e",
          "o",
          "u",
          "ɨ",
          "a"
        ]
      },
      {
        "symbol": "Ṽ",
        "members": [
          "ĩ",
          "ẽ",
          "õ",
          "ũ",
          "ɨ̃",
          "ã"
        ]
      }
    ],
    "glottolog_codes": [
      "TODO"
    ],
    "family": "TODO",
    "countries": "TODO",
    "coordinates": "TODO",
    "morphemes": [
      {
        "morpheme_id": "pɨ",
        "morpheme_type": "suffix",
        "underlying_form": "pɨ",
        "surface_forms": [
          "mɨ̃"
        ],
        "gloss": "LOC"
      },
      {
        "morpheme_id": "ʔi",
        "morpheme_type": "suffix",
        "underlying_form": "ʔi",
        "surface_forms": [
          "ʔĩ"
        ],
        "gloss": "DIM"
      }
    ],
    "phonemes": [
      {
        "phoneme": "p",
        "environments": [
          {
            "preceding": "",
            "following": "",
            "allophones": [
              {
                "processnames": [],
                "allophone": "p"
              }
            ]
          },
          {
            "preceding": "Ṽ+",
            "following": "",
            "allophones": [
              {
                "allophone": "mb",
                "processnames": [
                  "MPP=LN:ND"
                ]
              }
            ]
          },
          {
            "preceding": "TODO: &",
            "following": "TODO: &",
            "allophones": [
              {
                "allophone": "m",
                "processnames": [
                  "MPP=LNsyll:suffixes"
                ]
              }
            ]
          }
        ]
      },
      {
        "phoneme": "t",
        "environments": [
          {
            "preceding": "",
            "following": "",
            "allophones": [
              {
                "processnames": [],
                "allophone": "t"
              }
            ]
          },
          {
            "preceding": "Ṽ+",
            "following": "",
            "allophones": [
              {
                "allophone": "nd",
                "processnames": [
                  "MPP=LN:ND"
                ]
              }
            ]
          }
        ]
      },
      {
        "phoneme": "k",
        "environments": [
          {
            "preceding": "",
            "following": "",
            "allophones": [
              {
                "processnames": [],
                "allophone": "k"
              }
            ]
          },
          {
            "preceding": "Ṽ+",
            "following": "",
            "allophones": [
              {
                "allophone": "ŋɡ",
                "processnames": [
                  "MPP=LN:ND"
                ]
              }
            ]
          }
        ]
      },
      {
        "phoneme": "kʷ",
        "environments": [
          {
            "preceding": "",
            "following": "",
            "allophones": [
              {
                "processnames": [],
                "allophone": "kʷ"
              }
            ]
          },
          {
            "preceding": "Ṽ+",
            "following": "",
            "allophones": [
              {
                "allophone": "ŋɡʷ",
                "processnames": [
                  "MPP=LN:ND"
                ]
              }
            ]
          }
        ]
      },
      {
        "phoneme": "ʔ",
        "environments": [
          {
            "preceding": "",
            "following": "",
            "allophones": [
              {
                "processnames": [],
                "allophone": "ʔ"
              }
            ]
          }
        ]
      },
      {
        "phoneme": "ɡʷ",
        "environments": [
          {
            "preceding": "",
            "following": "",
            "allophones": [
              {
                "processnames": [],
                "allophone": "ɡʷ"
              }
            ]
          },
          {
            "preceding": "TODO: &",
            "following": "TODO: &",
            "allophones": [
              {
                "allophone": "ŋʷ",
                "processnames": [
                  "LDNH:leftward"
                ]
              }
            ]
          }
        ]
      },
      {
        "phoneme": "tʃ",
        "environments": [
          {
            "preceding": "",
            "following": "",
            "allophones": [
              {
                "processnames": [],
                "allophone": "tʃ"
              }
            ]
          }
        ]
      },
      {
        "phoneme": "dʒ",
        "environments": [
          {
            "preceding": "",
            "following": "",
            "allophones": [
              {
                "processnames": [],
                "allophone": "dʒ"
              }
            ]
          },
          {
            "preceding": "TODO: &",
            "following": "TODO: &",
            "allophones": [
              {
                "allophone": "ɲ",
                "processnames": [
                  "LDNH:leftward"
                ]
              }
            ]
          }
        ]
      },
      {
        "phoneme": "m",
        "environments": [
          {
            "preceding": "",
            "following": "",
            "allophones": [
              {
                "processnames": [],
                "allophone": "m"
              }
            ]
          },
          {
            "preceding": "",
            "following": "V",
            "allophones": [
              {
                "allophone": "mb",
                "processnames": [
                  "LO"
                ]
              }
            ]
          }
        ]
      },
      {
        "phoneme": "n",
        "environments": [
          {
            "preceding": "",
            "following": "",
            "allophones": [
              {
                "processnames": [],
                "allophone": "n"
              }
            ]
          },
          {
            "preceding": "",
            "following": "V",
            "allophones": [
              {
                "allophone": "nd",
                "processnames": [
                  "LO"
                ]
              }
            ]
          }
        ]
      },
      {
        "phoneme": "ŋ",
        "environments": [
          {
            "preceding": "",
            "following": "",
            "allophones": [
              {
                "processnames": [],
                "allophone": "ŋ"
              }
            ]
          },
          {
            "preceding": "",
            "following": "V",
            "allophones": [
              {
                "allophone": "ŋɡ",
                "processnames": [
                  "LO"
                ]
              }
            ]
          }
        ]
      },
      {
        "phoneme": "ŋʷ",
        "environments": [
          {
            "preceding": "",
            "following": "",
            "allophones": [
              {
                "processnames": [],
                "allophone": "ŋʷ"
              }
            ]
          },
          {
            "preceding": "",
            "following": "V",
            "allophones": [
              {
                "allophone": "ŋɡʷ",
                "processnames": [
                  "LO"
                ]
              }
            ]
          }
        ]
      },
      {
        "phoneme": "β",
        "environments": [
          {
            "preceding": "",
            "following": "",
            "allophones": [
              {
                "processnames": [],
                "allophone": "β"
              }
            ]
          },
          {
            "preceding": "TODO: US",
            "following": "TODO: US",
            "allophones": [
              {
                "allophone": "v",
                "processnames": [
                  "labiodentalization"
                ]
              }
            ]
          },
          {
            "preceding": "TODO: &",
            "following": "TODO: &",
            "allophones": [
              {
                "allophone": "β̃",
                "processnames": [
                  "LDNH:leftward"
                ]
              }
            ]
          }
        ]
      },
      {
        "phoneme": "ɾ",
        "environments": [
          {
            "preceding": "",
            "following": "",
            "allophones": [
              {
                "processnames": [],
                "allophone": "ɾ"
              }
            ]
          },
          {
            "preceding": "TODO: &",
            "following": "TODO: &",
            "allophones": [
              {
                "allophone": "ɾ̃",
                "processnames": [
                  "LDNH:leftward"
                ]
              }
            ]
          }
        ]
      },
      {
        "phoneme": "h",
        "environments": [
          {
            "preceding": "",
            "following": "",
            "allophones": [
              {
                "processnames": [],
                "allophone": "h"
              }
            ]
          }
        ]
      },
      {
        "phoneme": "w",
        "environments": [
          {
            "preceding": "",
            "following": "",
            "allophones": [
              {
                "processnames": [],
                "allophone": "w"
              }
            ]
          },
          {
            "preceding": "TODO: &",
            "following": "TODO: &",
            "allophones": [
              {
                "allophone": "w̃",
                "processnames": [
                  "LDNH:leftward"
                ]
              }
            ]
          }
        ]
      },
      {
        "phoneme": "i",
        "environments": [
          {
            "preceding": "",
            "following": "",
            "allophones": [
              {
                "processnames": [],
                "allophone": "i"
              }
            ]
          },
          {
            "preceding": "TODO: &",
            "following": "TODO: &",
            "allophones": [
              {
                "allophone": "ĩ",
                "processnames": [
                  "LDNH:leftward"
                ]
              }
            ]
          },
          {
            "preceding": "TODO: &",
            "following": "TODO: &",
            "allophones": [
              {
                "allophone": "ĩ",
                "processnames": [
                  "MPP=LNsyll:suffixes"
                ]
              }
            ]
          }
        ]
      },
      {
        "phoneme": "e",
        "environments": [
          {
            "preceding": "",
            "following": "",
            "allophones": [
              {
                "processnames": [],
                "allophone": "e"
              }
            ]
          },
          {
            "preceding": "TODO: &",
            "following": "TODO: &",
            "allophones": [
              {
                "allophone": "ẽ",
                "processnames": [
                  "LDNH:leftward"
                ]
              }
            ]
          }
        ]
      },
      {
        "phoneme": "o",
        "environments": [
          {
            "preceding": "",
            "following": "",
            "allophones": [
              {
                "processnames": [],
                "allophone": "o"
              }
            ]
          },
          {
            "preceding": "TODO: &",
            "following": "TODO: &",
            "allophones": [
              {
                "allophone": "õ",
                "processnames": [
                  "LDNH:leftward"
                ]
              }
            ]
          }
        ]
      },
      {
        "phoneme": "u",
        "environments": [
          {
            "preceding": "",
            "following": "",
            "allophones": [
              {
                "processnames": [],
                "allophone": "u"
              }
            ]
          },
          {
            "preceding": "TODO: &",
            "following": "TODO: &",
            "allophones": [
              {
                "allophone": "ũ",
                "processnames": [
                  "LDNH:leftward"
                ]
              }
            ]
          }
        ]
      },
      {
        "phoneme": "ɨ",
        "environments": [
          {
            "preceding": "",
            "following": "",
            "allophones": [
              {
                "processnames": [],
                "allophone": "ɨ"
              }
            ]
          },
          {
            "preceding": "TODO: &",
            "following": "TODO: &",
            "allophones": [
              {
                "allophone": "ɨ̃",
                "processnames": [
                  "LDNH:leftward"
                ]
              }
            ]
          },
          {
            "preceding": "TODO: &",
            "following": "TODO: &",
            "allophones": [
              {
                "allophone": "ɨ̃",
                "processnames": [
                  "MPP=LNsyll:suffixes"
                ]
              }
            ]
          }
        ]
      },
      {
        "phoneme": "a",
        "environments": [
          {
            "preceding": "",
            "following": "",
            "allophones": [
              {
                "processnames": [],
                "allophone": "a"
              }
            ]
          },
          {
            "preceding": "TODO: &",
            "following": "TODO: &",
            "allophones": [
              {
                "allophone": "ã",
                "processnames": [
                  "LDNH:leftward"
                ]
              }
            ]
          }
        ]
      },
      {
        "phoneme": "ĩ",
        "environments": [
          {
            "preceding": "",
            "following": "",
            "allophones": [
              {
                "processnames": [],
                "allophone": "ĩ"
              }
            ]
          }
        ]
      },
      {
        "phoneme": "ẽ",
        "environments": [
          {
            "preceding": "",
            "following": "",
            "allophones": [
              {
                "processnames": [],
                "allophone": "ẽ"
              }
            ]
          }
        ]
      },
      {
        "phoneme": "õ",
        "environments": [
          {
            "preceding": "",
            "following": "",
            "allophones": [
              {
                "processnames": [],
                "allophone": "õ"
              }
            ]
          }
        ]
      },
      {
        "phoneme": "ũ",
        "environments": [
          {
            "preceding": "",
            "following": "",
            "allophones": [
              {
                "processnames": [],
                "allophone": "ũ"
              }
            ]
          }
        ]
      },
      {
        "phoneme": "ɨ̃",
        "environments": [
          {
            "preceding": "",
            "following": "",
            "allophones": [
              {
                "processnames": [],
                "allophone": "ɨ̃"
              }
            ]
          }
        ]
      },
      {
        "phoneme": "ã",
        "environments": [
          {
            "preceding": "",
            "following": "",
            "allophones": [
              {
                "processnames": [],
                "allophone": "ã"
              }
            ]
          }
        ]
      }
    ],
    "processdetails": [
      {
        "processname": "LNsyll:suffixes",
        "processtype": "LNsyll",
        "description": "Rightward LDNH triggered by a root-final nasal vowel, nasalizing the suffixes /-pɨ/ and /-ʔi/ to [mɨ̃] and [ʔĩ]. Glottal stop is transparent for this process",
        "optionality": "categorical",
        "directionality": "rightward",
        "alternation_type": "morphophonological",
        "domain": "word-internal",
        "undergoers": {
          "segments": {
            "units": [
              "p",
              "ɨ",
              "i"
            ],
            "positional_restrictions": "NA"
          },
          "morphemes": {
            "units": [],
            "positional_restrictions": ""
          }
        },
        "triggers": {
          "segments": [
            {
              "units": [
                "Ṽ"
              ],
              "positional_restrictions": "root, final"
            }
          ],
          "morphemes": []
        },
        "transparent": {
          "segments": [
            {
              "units": [
                "ʔ"
              ],
              "positional_restrictions": ""
            }
          ],
          "morphemes": []
        },
        "opaque": {
          "segments": [
            {
              "units": [
                "Uncertain"
              ],
              "positional_restrictions": ""
            }
          ],
          "morphemes": []
        }
      },
      {
        "processname": "LN:ND",
        "processtype": "LN",
        "description": "In a root-suffix compound, a root-final nasal vowel triggers pre-nasalization and voicing of /p, t, k, kʷ/ to [mb, nd, ŋɡ, ŋɡʷ]",
        "optionality": "categorical",
        "directionality": "rightward",
        "alternation_type": "morphophonological",
        "domain": "word-internal",
        "undergoers": {
          "segments": {
            "units": [
              "p",
              "t",
              "k",
              "kʷ"
            ],
            "positional_restrictions": "suffix, initial"
          },
          "morphemes": {
            "units": [],
            "positional_restrictions": ""
          }
        },
        "triggers": {
          "segments": [
            {
              "units": [
                "Ṽ"
              ],
              "positional_restrictions": "root, final"
            }
          ],
          "morphemes": []
        },
        "transparent": {
          "segments": [
            {
              "units": [
                "NA"
              ],
              "positional_restrictions": ""
            }
          ],
          "morphemes": []
        },
        "opaque": {
          "segments": [
            {
              "units": [
                "NA"
              ],
              "positional_restrictions": ""
            }
          ],
          "morphemes": []
        }
      },
      {
        "processname": "LDNH:leftward",
        "processtype": "LDNH",
        "description": "A root-final stressed nasal vowel nasalizes oral vowels and voiced segments /ɾ, w, ɡʷ, β, dʒ/. Oral obstruents and fricatives are transparent",
        "optionality": "categorical",
        "directionality": "bidirectional",
        "alternation_type": "phonological",
        "domain": "word-internal",
        "undergoers": {
          "segments": {
            "units": [
              "V",
              "ɾ",
              "w",
              "ɡʷ",
              "β",
              "dʒ"
            ],
            "positional_restrictions": "None"
          },
          "morphemes": {
            "units": [],
            "positional_restrictions": ""
          }
        },
        "triggers": {
          "segments": [
            {
              "units": [
                "Ṽ́"
              ],
              "positional_restrictions": "root, final"
            }
          ],
          "morphemes": []
        },
        "transparent": {
          "segments": [
            {
              "units": [
                "p",
                "t",
                "tʃ",
                "k",
                "kʷ",
                "h"
              ],
              "positional_restrictions": ""
            }
          ],
          "morphemes": []
        },
        "opaque": {
          "segments": [
            {
              "units": [
                "Uncertain"
              ],
              "positional_restrictions": ""
            }
          ],
          "morphemes": []
        }
      },
      {
        "processname": "LO",
        "processtype": "LO",
        "description": "Nasal consonants /m, n, ŋ, ŋʷ/ surface as post-oralized [mb, nd, ŋɡ, ŋɡʷ] before an oral vowel",
        "optionality": "categorical",
        "directionality": "leftward",
        "alternation_type": "phonological",
        "domain": "word-internal",
        "undergoers": {
          "segments": {
            "units": [
              "m",
              "n",
              "ŋ",
              "ŋʷ"
            ],
            "positional_restrictions": "None"
          },
          "morphemes": {
            "units": [],
            "positional_restrictions": ""
          }
        },
        "triggers": {
          "segments": [
            {
              "units": [
                "V"
              ],
              "positional_restrictions": "None"
            }
          ],
          "morphemes": []
        },
        "transparent": {
          "segments": [
            {
              "units": [
                "NA"
              ],
              "positional_restrictions": ""
            }
          ],
          "morphemes": []
        },
        "opaque": {
          "segments": [
            {
              "units": [
                "NA"
              ],
              "positional_restrictions": ""
            }
          ],
          "morphemes": []
        }
      }
    ],
    "tone": "TODO",
    "laryngeal_harmony": "TODO",
    "notes": "\"Note that the voiceless fricative /s/ of Mbya seems to be attested only in one word, sapukai (‘to shout’), which may have been borrowed from Paraguayan Guarani\" (Thomas, 2014:79)."
  }
]